{"title":"澎湃思想 私家历史","url":"https://m.thepaper.cn/list_25457","favicon":"https://m.thepaper.cn/favicon.ico","elements":[{"title":"海外考古大家访谈｜菅谷文则：我是北京大学考古系培养出来的","contents":"<a class=\"index_inherit__wl1Pg index_imgBox__ksJ6m imgBox\" href=\"/newsDetail_forward_28936911\"><img src=\"https://imagecloud.thepaper.cn/thepaper/image/324/755/888.jpg?x-oss-process=image/resize,w_332\" alt=\"海外考古大家访谈｜菅谷文则：我是北京大学考古系培养出来的\"></a><div class=\"index_contentBox__070hn\"><a class=\"index_inherit__wl1Pg\" href=\"/newsDetail_forward_28936911\"><h3 class=\"index_title__aGAqD\">海外考古大家访谈｜菅谷文则：我是北京大学考古系培养出来的</h3></a><div class=\"index_spaceBox__YFy6S\"><div class=\"adm-space adm-space-horizontal\" style=\"--gap-horizontal:0.2rem\"><div class=\"adm-space-item\"><div class=\"index_extra__M2kfN\"><a class=\"index_inherit__wl1Pg\" href=\"/list_25457\">私家历史</a></div></div><div class=\"adm-space-item\"><span>3小时前</span></div></div><span class=\"index_item_label__RwoaG\"></span></div></div>","link":"https://m.thepaper.cn/newsDetail_forward_28936911","retrieved":1728106592559},{"title":"防微杜渐：康熙皇帝对普通太监的管理","contents":"<a class=\"index_inherit__wl1Pg index_imgBox__ksJ6m imgBox\" href=\"/newsDetail_forward_28827183\"><img src=\"https://imagecloud.thepaper.cn/thepaper/image/323/309/568.jpg?x-oss-process=image/resize,w_332\" alt=\"防微杜渐：康熙皇帝对普通太监的管理\"></a><div class=\"index_contentBox__070hn\"><a class=\"index_inherit__wl1Pg\" href=\"/newsDetail_forward_28827183\"><h3 class=\"index_title__aGAqD\">防微杜渐：康熙皇帝对普通太监的管理</h3></a><div class=\"index_spaceBox__YFy6S\"><div class=\"adm-space adm-space-horizontal\" style=\"--gap-horizontal:0.2rem\"><div class=\"adm-space-item\"><div class=\"index_extra__M2kfN\"><a class=\"index_inherit__wl1Pg\" href=\"/list_25457\">私家历史</a></div></div><div class=\"adm-space-item\"><span>3小时前</span></div></div><span class=\"index_item_label__RwoaG\"></span></div></div>","link":"https://m.thepaper.cn/newsDetail_forward_28827183","retrieved":1728106592561},{"title":"1870-1930年美国烟草公司在中国的扩张","contents":"<a class=\"index_inherit__wl1Pg index_imgBox__ksJ6m imgBox\" href=\"/newsDetail_forward_28665925\"><img src=\"https://imagecloud.thepaper.cn/thepaper/image/321/234/398.jpeg?x-oss-process=image/resize,w_332\" alt=\"1870-1930年美国烟草公司在中国的扩张\"></a><div class=\"index_contentBox__070hn\"><a class=\"index_inherit__wl1Pg\" href=\"/newsDetail_forward_28665925\"><h3 class=\"index_title__aGAqD\">1870-1930年美国烟草公司在中国的扩张</h3></a><div class=\"index_spaceBox__YFy6S\"><div class=\"adm-space adm-space-horizontal\" style=\"--gap-horizontal:0.2rem\"><div class=\"adm-space-item\"><div class=\"index_extra__M2kfN\"><a class=\"index_inherit__wl1Pg\" href=\"/list_25457\">私家历史</a></div></div><div class=\"adm-space-item\"><span>1天前</span></div></div><span class=\"index_item_label__RwoaG\"></span></div></div>","link":"https://m.thepaper.cn/newsDetail_forward_28665925","retrieved":1728020302951},{"title":"宋神宗“建储”与“宣仁之诬”","contents":"<a class=\"index_inherit__wl1Pg index_imgBox__ksJ6m imgBox\" href=\"/newsDetail_forward_27520953\"><img src=\"https://imagecloud.thepaper.cn/thepaper/image/313/220/170.jpg?x-oss-process=image/resize,w_332\" alt=\"宋神宗“建储”与“宣仁之诬”\"></a><div class=\"index_contentBox__070hn\"><a class=\"index_inherit__wl1Pg\" href=\"/newsDetail_forward_27520953\"><h3 class=\"index_title__aGAqD\">宋神宗“建储”与“宣仁之诬”</h3></a><div class=\"index_spaceBox__YFy6S\"><div class=\"adm-space adm-space-horizontal\" style=\"--gap-horizontal:0.2rem\"><div class=\"adm-space-item\"><div class=\"index_extra__M2kfN\"><a class=\"index_inherit__wl1Pg\" href=\"/list_25457\">私家历史</a></div></div><div class=\"adm-space-item\"><span>1天前</span></div></div><span class=\"index_item_label__RwoaG\"></span></div></div>","link":"https://m.thepaper.cn/newsDetail_forward_27520953","retrieved":1728020302951},{"title":"隐于《顾颉刚日记》背后的“打工人”汪安之","contents":"<a class=\"index_inherit__wl1Pg index_imgBox__ksJ6m imgBox\" href=\"/newsDetail_forward_28677519\"><img src=\"https://imagecloud.thepaper.cn/thepaper/image/323/887/54.jpg?x-oss-process=image/resize,w_332\" alt=\"隐于《顾颉刚日记》背后的“打工人”汪安之\"></a><div class=\"index_contentBox__070hn\"><a class=\"index_inherit__wl1Pg\" href=\"/newsDetail_forward_28677519\"><h3 class=\"index_title__aGAqD\">隐于《顾颉刚日记》背后的“打工人”汪安之</h3></a><div class=\"index_spaceBox__YFy6S\"><div class=\"adm-space adm-space-horizontal\" style=\"--gap-horizontal:0.2rem\"><div class=\"adm-space-item\"><div class=\"index_extra__M2kfN\"><a class=\"index_inherit__wl1Pg\" href=\"/list_25457\">私家历史</a></div></div><div class=\"adm-space-item\"><span>2天前</span></div></div><span class=\"index_item_label__RwoaG\"></span></div></div>","link":"https://m.thepaper.cn/newsDetail_forward_28677519","retrieved":1727933889838},{"title":"蛋壳乾坤：近代中国鸡蛋是如何走出国门的？","contents":"<a class=\"index_inherit__wl1Pg index_imgBox__ksJ6m imgBox\" href=\"/newsDetail_forward_28920100\"><img src=\"https://imagecloud.thepaper.cn/thepaper/image/324/492/53.jpg?x-oss-process=image/resize,w_332\" alt=\"蛋壳乾坤：近代中国鸡蛋是如何走出国门的？\"></a><div class=\"index_contentBox__070hn\"><a class=\"index_inherit__wl1Pg\" href=\"/newsDetail_forward_28920100\"><h3 class=\"index_title__aGAqD\">蛋壳乾坤：近代中国鸡蛋是如何走出国门的？</h3></a><div class=\"index_spaceBox__YFy6S\"><div class=\"adm-space adm-space-horizontal\" style=\"--gap-horizontal:0.2rem\"><div class=\"adm-space-item\"><div class=\"index_extra__M2kfN\"><a class=\"index_inherit__wl1Pg\" href=\"/list_25457\">私家历史</a></div></div><div class=\"adm-space-item\"><span>2天前</span></div></div><span class=\"index_item_label__RwoaG\"></span></div></div>","link":"https://m.thepaper.cn/newsDetail_forward_28920100","retrieved":1727933889838},{"title":"探寻联结的历史——“世界史视野下的中国当代史研究”学术研讨会侧记","contents":"<a class=\"index_inherit__wl1Pg index_imgBox__ksJ6m imgBox\" href=\"/newsDetail_forward_28907949\"><img src=\"https://imagecloud.thepaper.cn/thepaper/image/324/319/929.png?x-oss-process=image/resize,w_332\" alt=\"探寻联结的历史——“世界史视野下的中国当代史研究”学术研讨会侧记\"></a><div class=\"index_contentBox__070hn\"><a class=\"index_inherit__wl1Pg\" href=\"/newsDetail_forward_28907949\"><h3 class=\"index_title__aGAqD\">探寻联结的历史——“世界史视野下的中国当代史研究”学术研讨会侧记</h3></a><div class=\"index_spaceBox__YFy6S\"><div class=\"adm-space adm-space-horizontal\" style=\"--gap-horizontal:0.2rem\"><div class=\"adm-space-item\"><div class=\"index_extra__M2kfN\"><a class=\"index_inherit__wl1Pg\" href=\"/list_25457\">私家历史</a></div></div><div class=\"adm-space-item\"><span>2天前</span></div><div class=\"adm-space-item\"><span> <!-- -->12<!-- -->评<!-- --></span></div></div><span class=\"index_item_label__RwoaG\"></span></div></div>","link":"https://m.thepaper.cn/newsDetail_forward_28907949","retrieved":1727890486669},{"title":"“经典地中海”——地中海历史的五个阶段","contents":"<a class=\"index_inherit__wl1Pg index_imgBox__ksJ6m imgBox\" href=\"/newsDetail_forward_28652200\"><img src=\"https://imagecloud.thepaper.cn/thepaper/image/321/59/970.jpg?x-oss-process=image/resize,w_332\" alt=\"“经典地中海”——地中海历史的五个阶段\"></a><div class=\"index_contentBox__070hn\"><a class=\"index_inherit__wl1Pg\" href=\"/newsDetail_forward_28652200\"><h3 class=\"index_title__aGAqD\">“经典地中海”——地中海历史的五个阶段</h3></a><div class=\"index_spaceBox__YFy6S\"><div class=\"adm-space adm-space-horizontal\" style=\"--gap-horizontal:0.2rem\"><div class=\"adm-space-item\"><div class=\"index_extra__M2kfN\"><a class=\"index_inherit__wl1Pg\" href=\"/list_25457\">私家历史</a></div></div><div class=\"adm-space-item\"><span>3天前</span></div></div><span class=\"index_item_label__RwoaG\"></span></div></div>","link":"https://m.thepaper.cn/newsDetail_forward_28652200","retrieved":1727847473160},{"title":"完整的残稿——《被记忆的西周史》译后记","contents":"<a class=\"index_inherit__wl1Pg index_imgBox__ksJ6m imgBox\" href=\"/newsDetail_forward_28919412\"><img src=\"https://imagecloud.thepaper.cn/thepaper/image/324/485/91.jpeg?x-oss-process=image/resize,w_332\" alt=\"完整的残稿——《被记忆的西周史》译后记\"></a><div class=\"index_contentBox__070hn\"><a class=\"index_inherit__wl1Pg\" href=\"/newsDetail_forward_28919412\"><h3 class=\"index_title__aGAqD\">完整的残稿——《被记忆的西周史》译后记</h3></a><div class=\"index_spaceBox__YFy6S\"><div class=\"adm-space adm-space-horizontal\" style=\"--gap-horizontal:0.2rem\"><div class=\"adm-space-item\"><div class=\"index_extra__M2kfN\"><a class=\"index_inherit__wl1Pg\" href=\"/list_25457\">私家历史</a></div></div><div class=\"adm-space-item\"><span>4天前</span></div></div><span class=\"index_item_label__RwoaG\"></span></div></div>","link":"https://m.thepaper.cn/newsDetail_forward_28919412","retrieved":1727761086483},{"title":"刘未：南宋临安城在中国古代都城史上的地位","contents":"<a class=\"index_inherit__wl1Pg index_imgBox__ksJ6m imgBox\" href=\"/newsDetail_forward_28826930\"><img src=\"https://imagecloud.thepaper.cn/thepaper/image/323/306/604.jpg?x-oss-process=image/resize,w_332\" alt=\"刘未：南宋临安城在中国古代都城史上的地位\"></a><div class=\"index_contentBox__070hn\"><a class=\"index_inherit__wl1Pg\" href=\"/newsDetail_forward_28826930\"><h3 class=\"index_title__aGAqD\">刘未：南宋临安城在中国古代都城史上的地位</h3></a><div class=\"index_spaceBox__YFy6S\"><div class=\"adm-space adm-space-horizontal\" style=\"--gap-horizontal:0.2rem\"><div class=\"adm-space-item\"><div class=\"index_extra__M2kfN\"><a class=\"index_inherit__wl1Pg\" href=\"/list_25457\">私家历史</a></div></div><div class=\"adm-space-item\"><span>5天前</span></div></div><span class=\"index_item_label__RwoaG\"></span></div></div>","link":"https://m.thepaper.cn/newsDetail_forward_28826930","retrieved":1727674686584}]}