{"title":"澎湃思想 上海书评","url":"https://m.thepaper.cn/list_26878","favicon":"https://m.thepaper.cn/favicon.ico","elements":[{"title":"上海书评周刊","contents":"<a class=\"inherit__bjgYt imgBox__LkGL_ imgBox\" href=\"https://html.thepaper.cn/collection/shanghaishuping260125\"><img src=\"https://imgpai.thepaper.cn/newpai/image/1769297527392_6reb1w_1769297527393.png?x-oss-process=image/resize,w_332\" alt=\"上海书评周刊\"></a><div class=\"contentBox__E6I7I\"><a class=\"inherit__bjgYt\" href=\"https://html.thepaper.cn/collection/shanghaishuping260125\"><h3 class=\"title__vUn1u\">上海书评周刊</h3></a><div class=\"spaceBox__YfTQz\"><div class=\"adm-space adm-space-horizontal\" style=\"--gap-horizontal:0.2rem\"><div class=\"adm-space-item\"><div class=\"extra__fXAry\"><a class=\"inherit__bjgYt\" href=\"/list_26878\">上海书评</a></div></div><div class=\"adm-space-item\"><span>3天前</span></div><div class=\"adm-space-item\"><span> <!-- -->150<!-- -->评</span></div></div><span class=\"item_label__LUQ2u\">推荐</span></div></div>","link":"https://html.thepaper.cn/collection/shanghaishuping260125","retrieved":1769310454026},{"title":"张巍｜尼采的“慢读艺术”","contents":"<a class=\"inherit__bjgYt imgBox__LkGL_ imgBox\" href=\"/newsDetail_forward_32473092\"><img src=\"https://imgpai.thepaper.cn/newpai/image/1769498884649_sWMh8T_1769498884851.png?x-oss-process=image/resize,w_332\" alt=\"张巍｜尼采的“慢读艺术”\"></a><div class=\"contentBox__E6I7I\"><a class=\"inherit__bjgYt\" href=\"/newsDetail_forward_32473092\"><h3 class=\"title__vUn1u\">张巍｜尼采的“慢读艺术”</h3></a><div class=\"spaceBox__YfTQz\"><div class=\"adm-space adm-space-horizontal\" style=\"--gap-horizontal:0.2rem\"><div class=\"adm-space-item\"><div class=\"extra__fXAry\"><a class=\"inherit__bjgYt\" href=\"/list_26878\">上海书评</a></div></div><div class=\"adm-space-item\"><span>2小时前</span></div><div class=\"adm-space-item\"><span> <!-- -->12<!-- -->评</span></div></div><span class=\"item_label__LUQ2u\"></span></div></div>","link":"https://m.thepaper.cn/newsDetail_forward_32473092","retrieved":1769579323791},{"title":"吕厚量｜女神、娼妓、妻子与女奴：古典时代的女性生活","contents":"<a class=\"inherit__bjgYt imgBox__LkGL_ imgBox\" href=\"/newsDetail_forward_32415806\"><img src=\"https://imgpai.thepaper.cn/newpai/image/1768817179264_pyXQBn_1768817179483.png?x-oss-process=image/resize,w_332\" alt=\"吕厚量｜女神、娼妓、妻子与女奴：古典时代的女性生活\"></a><div class=\"contentBox__E6I7I\"><a class=\"inherit__bjgYt\" href=\"/newsDetail_forward_32415806\"><h3 class=\"title__vUn1u\">吕厚量｜女神、娼妓、妻子与女奴：古典时代的女性生活</h3></a><div class=\"spaceBox__YfTQz\"><div class=\"adm-space adm-space-horizontal\" style=\"--gap-horizontal:0.2rem\"><div class=\"adm-space-item\"><div class=\"extra__fXAry\"><a class=\"inherit__bjgYt\" href=\"/list_26878\">上海书评</a></div></div><div class=\"adm-space-item\"><span>1天前</span></div><div class=\"adm-space-item\"><span> <!-- -->12<!-- -->评</span></div></div><span class=\"item_label__LUQ2u\"></span></div></div>","link":"https://m.thepaper.cn/newsDetail_forward_32415806","retrieved":1769492858940},{"title":"林小英｜优绩主义的双重面具","contents":"<a class=\"inherit__bjgYt imgBox__LkGL_ imgBox\" href=\"/newsDetail_forward_32461532\"><img src=\"https://imgpai.thepaper.cn/newpai/image/1769336436593_EFMk2H_1769336481883.jpg?x-oss-process=image/resize,w_332\" alt=\"林小英｜优绩主义的双重面具\"></a><div class=\"contentBox__E6I7I\"><a class=\"inherit__bjgYt\" href=\"/newsDetail_forward_32461532\"><h3 class=\"title__vUn1u\">林小英｜优绩主义的双重面具</h3></a><div class=\"spaceBox__YfTQz\"><div class=\"adm-space adm-space-horizontal\" style=\"--gap-horizontal:0.2rem\"><div class=\"adm-space-item\"><div class=\"extra__fXAry\"><a class=\"inherit__bjgYt\" href=\"/list_26878\">上海书评</a></div></div><div class=\"adm-space-item\"><span>2天前</span></div><div class=\"adm-space-item\"><span> <!-- -->15<!-- -->评</span></div></div><span class=\"item_label__LUQ2u\"></span></div></div>","link":"https://m.thepaper.cn/newsDetail_forward_32461532","retrieved":1769406683684},{"title":"里亚·格林菲尔德谈民族主义与现代心智","contents":"<a class=\"inherit__bjgYt imgBox__LkGL_ imgBox\" href=\"/newsDetail_forward_32457239\"><img src=\"https://imgpai.thepaper.cn/newpai/image/1769297261160_GAjSzK_1769297261404.png?x-oss-process=image/resize,w_332\" alt=\"里亚·格林菲尔德谈民族主义与现代心智\"></a><div class=\"contentBox__E6I7I\"><a class=\"inherit__bjgYt\" href=\"/newsDetail_forward_32457239\"><h3 class=\"title__vUn1u\">里亚·格林菲尔德谈民族主义与现代心智</h3></a><div class=\"spaceBox__YfTQz\"><div class=\"adm-space adm-space-horizontal\" style=\"--gap-horizontal:0.2rem\"><div class=\"adm-space-item\"><div class=\"extra__fXAry\"><a class=\"inherit__bjgYt\" href=\"/list_26878\">上海书评</a></div></div><div class=\"adm-space-item\"><span>3天前</span></div><div class=\"adm-space-item\"><span> <!-- -->15<!-- -->评</span></div></div><span class=\"item_label__LUQ2u\"></span></div></div>","link":"https://m.thepaper.cn/newsDetail_forward_32457239","retrieved":1769310454030},{"title":"蔡伟杰谈从马可波罗到马戛尔尼的中国与世界","contents":"<a class=\"inherit__bjgYt imgBox__LkGL_ imgBox\" href=\"/newsDetail_forward_32423307\"><img src=\"https://imgpai.thepaper.cn/newpai/image/1769180815253_2hw6KR_1769180815587.png?x-oss-process=image/resize,w_332\" alt=\"蔡伟杰谈从马可波罗到马戛尔尼的中国与世界\"></a><div class=\"contentBox__E6I7I\"><a class=\"inherit__bjgYt\" href=\"/newsDetail_forward_32423307\"><h3 class=\"title__vUn1u\">蔡伟杰谈从马可波罗到马戛尔尼的中国与世界</h3></a><div class=\"spaceBox__YfTQz\"><div class=\"adm-space adm-space-horizontal\" style=\"--gap-horizontal:0.2rem\"><div class=\"adm-space-item\"><div class=\"extra__fXAry\"><a class=\"inherit__bjgYt\" href=\"/list_26878\">上海书评</a></div></div><div class=\"adm-space-item\"><span>4天前</span></div></div><span class=\"item_label__LUQ2u\"></span></div></div>","link":"https://m.thepaper.cn/newsDetail_forward_32423307","retrieved":1769310454031},{"title":"毛尖谈张爱玲：对“钱”的赤裸告白，有一种明亮的革命性｜播客","contents":"<a class=\"inherit__bjgYt imgBox__LkGL_ imgBox\" href=\"/newsDetail_forward_32392504\"><img src=\"https://imgpai.thepaper.cn/newpai/image/1768473115564_p1JeA2_1768473115832.png?x-oss-process=image/resize,w_332\" alt=\"毛尖谈张爱玲：对“钱”的赤裸告白，有一种明亮的革命性｜播客\"><span class=\"watermark_duration\"><i class=\"icon_common icon_play\"></i><i class=\"watermark_num\">03:32</i></span></a><div class=\"contentBox__E6I7I\"><a class=\"inherit__bjgYt\" href=\"/newsDetail_forward_32392504\"><h3 class=\"title__vUn1u\">毛尖谈张爱玲：对“钱”的赤裸告白，有一种明亮的革命性｜播客</h3></a><div class=\"spaceBox__YfTQz\"><div class=\"adm-space adm-space-horizontal\" style=\"--gap-horizontal:0.2rem\"><div class=\"adm-space-item\"><div class=\"extra__fXAry\"><a class=\"inherit__bjgYt\" href=\"/list_26878\">上海书评</a></div></div><div class=\"adm-space-item\"><span>5天前</span></div><div class=\"adm-space-item\"><span> <!-- -->12<!-- -->评</span></div></div><span class=\"item_label__LUQ2u\"></span></div></div>","link":"https://m.thepaper.cn/newsDetail_forward_32392504","retrieved":1769310454035},{"title":"段德敏｜从革命的街头到身份迷途：勒弗与欧洲左翼的世纪苍黄","contents":"<a class=\"inherit__bjgYt imgBox__LkGL_ imgBox\" href=\"/newsDetail_forward_32391142\"><img src=\"https://imgpai.thepaper.cn/newpai/image/1768465074905_eC1tBX_1768465075042.png?x-oss-process=image/resize,w_332\" alt=\"段德敏｜从革命的街头到身份迷途：勒弗与欧洲左翼的世纪苍黄\"></a><div class=\"contentBox__E6I7I\"><a class=\"inherit__bjgYt\" href=\"/newsDetail_forward_32391142\"><h3 class=\"title__vUn1u\">段德敏｜从革命的街头到身份迷途：勒弗与欧洲左翼的世纪苍黄</h3></a><div class=\"spaceBox__YfTQz\"><div class=\"adm-space adm-space-horizontal\" style=\"--gap-horizontal:0.2rem\"><div class=\"adm-space-item\"><div class=\"extra__fXAry\"><a class=\"inherit__bjgYt\" href=\"/list_26878\">上海书评</a></div></div><div class=\"adm-space-item\"><span>5天前</span></div><div class=\"adm-space-item\"><span> <!-- -->15<!-- -->评</span></div></div><span class=\"item_label__LUQ2u\"></span></div></div>","link":"https://m.thepaper.cn/newsDetail_forward_32391142","retrieved":1769310454036},{"title":"惠春寿评《被雇佣的人》丨在工作中寻求正义？","contents":"<a class=\"inherit__bjgYt imgBox__LkGL_ imgBox\" href=\"/newsDetail_forward_32423269\"><img src=\"https://imgpai.thepaper.cn/newpai/image/1768886663703_GZfxtA_1768886663891.png?x-oss-process=image/resize,w_332\" alt=\"惠春寿评《被雇佣的人》丨在工作中寻求正义？\"></a><div class=\"contentBox__E6I7I\"><a class=\"inherit__bjgYt\" href=\"/newsDetail_forward_32423269\"><h3 class=\"title__vUn1u\">惠春寿评《被雇佣的人》丨在工作中寻求正义？</h3></a><div class=\"spaceBox__YfTQz\"><div class=\"adm-space adm-space-horizontal\" style=\"--gap-horizontal:0.2rem\"><div class=\"adm-space-item\"><div class=\"extra__fXAry\"><a class=\"inherit__bjgYt\" href=\"/list_26878\">上海书评</a></div></div><div class=\"adm-space-item\"><span>6天前</span></div></div><span class=\"item_label__LUQ2u\"></span></div></div>","link":"https://m.thepaper.cn/newsDetail_forward_32423269","retrieved":1769310454037},{"title":"李公明｜一周书记：像汉娜·阿伦特那样去思考与……反抗","contents":"<a class=\"inherit__bjgYt imgBox__LkGL_ imgBox\" href=\"/newsDetail_forward_32433623\"><img src=\"https://imgpai.thepaper.cn/newpai/image/1769009776767_YdyAXz_1769009777170.png?x-oss-process=image/resize,w_332\" alt=\"李公明｜一周书记：像汉娜·阿伦特那样去思考与……反抗\"></a><div class=\"contentBox__E6I7I\"><a class=\"inherit__bjgYt\" href=\"/newsDetail_forward_32433623\"><h3 class=\"title__vUn1u\">李公明｜一周书记：像汉娜·阿伦特那样去思考与……反抗</h3></a><div class=\"spaceBox__YfTQz\"><div class=\"adm-space adm-space-horizontal\" style=\"--gap-horizontal:0.2rem\"><div class=\"adm-space-item\"><div class=\"extra__fXAry\"><a class=\"inherit__bjgYt\" href=\"/list_26878\">上海书评</a></div></div><div class=\"adm-space-item\"><span>6天前</span></div><div class=\"adm-space-item\"><span> <!-- -->12<!-- -->评</span></div></div><span class=\"item_label__LUQ2u\"></span></div></div>","link":"https://m.thepaper.cn/newsDetail_forward_32433623","retrieved":1769310454038}]}